{
	"miniprogramRoot": "dist/",
	"projectname": "what-to-eat",
	"description": "a project to choose what to eat",
	"appid": "wx776476e679b67f1a",
	"setting": {
		"urlCheck": false,
		"es6": true,
		"postcss": false,
		"minified": false,
		"newFeature": true,
		"autoAudits": false,
		"checkInvalidKey": true,
		"checkSiteMap": true,
		"uploadWithSourceMap": true,
		"babelSetting": {
			"ignore": [],
			"disablePlugins": [],
			"outputPath": ""
		}
	},
	"compileType": "miniprogram",
	"simulatorType": "wechat",
	"simulatorPluginLibVersion": {},
	"condition": {}
}